django_channels_notifications/__init__.py
django_channels_notifications/apps.py
django_channels_notifications/models.py
django_channels_notifications/core/__init__.py
django_channels_notifications/core/notifiable.py
django_channels_notifications/core/notification.py
django_channels_notifications/core/notification_sender.py
django_channels_notifications/core/channels/__init__.py
django_channels_notifications/core/channels/base_channel.py
django_channels_notifications/core/channels/database_channel.py
django_channels_notifications/core/channels/mail_channel.py
django_channels_notifications/core/channels/unifonic_channel.py
django_channels_notifications/management/__init__.py
django_channels_notifications/management/commands/__init__.py
django_channels_notifications/management/commands/createchannel.py
django_channels_notifications/management/commands/createnotification.py
django_channels_notifications/migrations/0001_initial.py
django_channels_notifications/migrations/0002_auto_20191214_1954.py
django_channels_notifications/migrations/__init__.py
django_channels_notifications-1.1.dist-info/METADATA
django_channels_notifications-1.1.dist-info/WHEEL
django_channels_notifications-1.1.dist-info/top_level.txt
django_channels_notifications-1.1.dist-info/RECORD
