Metadata-Version: 2.1
Name: django-channels-notifications
Version: 1.1
Summary: Django Channels Notifications
Home-page: https://github.com/Abdelhadi92/django-channels-notifications
Author: Abdelhadi Abu-Shamleh
Author-email: abushamleh92@gmail.com
License: BSD
Keywords: Django Channels Notifications
Platform: UNKNOWN
Classifier: Environment :: Web Environment
Classifier: Framework :: Django
Classifier: License :: OSI Approved :: BSD License
Classifier: Operating System :: OS Independent
Classifier: Development Status :: 5 - Production/Stable
Classifier: Programming Language :: Python
Classifier: Programming Language :: Python :: 3
Classifier: Programming Language :: Python :: 3.4
Classifier: Programming Language :: Python :: 3.5
Classifier: Programming Language :: Python :: 3.6
Classifier: Programming Language :: Python :: 3.7
